LICENSE
setup.py
Liberty/__init__.py
Liberty/dreamer.py
LibertyDreamer.egg-info/PKG-INFO
LibertyDreamer.egg-info/SOURCES.txt
LibertyDreamer.egg-info/dependency_links.txt
LibertyDreamer.egg-info/requires.txt
LibertyDreamer.egg-info/top_level.txt