Metadata-Version: 2.1
Name: LibertyDreamer
Version: 1.0.1
Summary: Free yourself with tools that increase the ease and possibilities of your project.
Author: Benfica
License: MIT License
Keywords: chatbot,liberty,freedom,bot,chat
License-File: LICENSE
